pyluxafor_mac/__init__.py
pyluxafor_mac/pyluxafor_mac.py
pyluxafor_mac-0.0.1.dist-info/METADATA
pyluxafor_mac-0.0.1.dist-info/WHEEL
pyluxafor_mac-0.0.1.dist-info/entry_points.txt
pyluxafor_mac-0.0.1.dist-info/top_level.txt
pyluxafor_mac-0.0.1.dist-info/RECORD
